{
    "headline": "Banking And Finance Heres What We Know About Ftx Collapse",
    "summary": "In the complicated world of cryptocurrency, what should we make ofFTX's demise?In Summary:The cryptocurrency exchange, which had an estimated value of$32 billionearlier this year,\u00a0recentlyfiled for bankruptcyafter freezing\u00a0customer withdrawals\u00a0and reports that it spent customer funds on risky investments. That followed\u00a0a rapid rise from its founding in 2019\u00a0tomulti-million dollar advertising dealsand becoming the world's third-largest crypto marketplace. Because FTX is based in the Bahamas, it's largely\u00a0shielded from U.S. regulations on trading and selling investments to the public.By the Numbers:Founder Sam Bankman-Fried is accused of transferring roughly $10 billion of customer funds from FTX to his\u00a0investing company, Alameda Research.\u00a0At least $1 billion of customer funds has vanished from FTX. Before the crash, he\u00a0donated roughly $40 million to Democrats in the 2022 election cycle, making him the party's second-ranked donor behind George Soros. He also made seven-figure\u00a0grants to news sources such as ProPublica and The Intercept.What's Next:The Manhattan U.S. attorney\u2019s office is nowinvestigatingFTX\u2019s collapse. It's unclear if Bankman-Fried will be charged, but experts agree that the incident will lead to heavier crypto regulation. Currently, no protections exist for those who lost money.How the Media Covered It:FTX's collapse and corruption have been a focus of coverage across the spectrum. Some right-rated sourcesquestionedwhether Bankman-Fried's donations to news companies had made them less likely to investigate him.",
    "story": {
        "left": [
            "https://www.washingtonpost.com/technology/2022/11/24/ftx-bahamas-albany-fried/"
        ],
        "center": [
            "https://www.wsj.com/articles/ftx-and-sam-bankman-fried-your-guide-to-the-crypto-crash-11669375609"
        ],
        "right": [
            "https://www.foxbusiness.com/politics/ftx-founder-sam-bankman-fried-hot-seat-senate-inquiries-criminal-probes-move-forward"
        ]
    }
}