{
    "headline": "Former Senator John Warner Virginia Dies Age 94",
    "summary": "Former Senator\u00a0John Warner, who represented Virginia in the U.S. Senate for three decades, has died at age 94.\u00a0 He served as Chairman of the Senate Armed Services Committee and played a central role in shaping military affairs legislation.Warner served in the U.S. Navy during World War II and the Marines during the Korean War. He later served as secretary of the Navy and as a Republican U.S. senator from 1979 through 2009.\u00a0 He\u00a0was also married to actress Elizabeth Taylor from 1976 to 1982.",
    "story": {
        "left": [
            "https://www.cnn.com/2021/05/26/politics/virginia-senator-john-warner-dies/index.html"
        ],
        "center": [
            "https://thehill.com/homenews/senate/555465-former-va-sen-john-warner-dies-at-94"
        ],
        "right": [
            "https://www.foxnews.com/politics/former-sen-john-warner-dead-age-94-elizabeth-taylor-marriage"
        ]
    }
}