{
    "headline": "Lgbtq Issues Bipartisan Senators Announce Deal Codify Same Sex Marriage",
    "summary": "A bipartisan group of Senate negotiators said Monday that they had reached a deal tocodify same-sex marriage,thanks to anamendmentaddressing some senators\u2019 religious liberty concerns.Key Quotes:Sens. Rob Portman (R-Ohio), Tammy Baldwin (D-Wis.), Susan Collins (R-Maine), Kyrsten Sinema (D-Ariz.), and Thom Tillis (R-N.C.) released astatementon their agreement, saying, \u201cThrough bipartisan collaboration, we\u2019ve crafted commonsense language to confirm that this legislation fully respects and protects Americans\u2019 religious liberties and diverse beliefs, while leaving intact the core mission of the legislation to protect marriage equality. We look forward to this legislation coming to the floor and are confident that this amendment has helped earn the broad, bipartisan support needed to pass our commonsense legislation into law.\u201dWhat\u2019s Next:Senate Majority Leader Chuck Schumer (D-N.Y.) reportedly scheduled a test vote for the bill on Wednesday. Senate Democrats, who would likely all support the bill, would need at least 10 Senate Republicans to overcome the possibility of a filibuster. Same-sex marriage is justone of several issues Congress is preparing to tacklebefore midtermelection winnersare sworn in next year.How the Media Covered It:Coverage was common in left and center-rated outlets but relatively rare in right-rated outlets on Monday evening.\u00a0Coverage varied on using the term\u201cmarriage equality\u201doutside of quotes.",
    "story": {
        "left": [
            "https://www.lgbtqnation.com/2022/11/senate-vote-revised-marriage-equality-bill-week/"
        ],
        "center": [
            "https://thehill.com/homenews/senate/3735128-senators-strike-deal-on-bill-to-codify-supreme-courts-same-sex-marriage-protections/"
        ],
        "right": [
            "https://www.washingtontimes.com/news/2022/nov/14/charles-schumer-tees-vote-codify-same-sex-marriage/"
        ]
    }
}