{
    "headline": "Perspectives Pride Month 2021",
    "summary": "President Joe Biden formally declared Pride Monthon Tuesday, saying, \"we recognize the resilience and determination of the many individuals who are fighting to live freely and authentically.\" This marked\u00a0a departure from former President Donald Trump, who never\u00a0acknowledged the celebrationoutside of a 2019 tweet thread. Pride Month received its first official declaration\u00a0fromformer President Bill Clinton in June 1999. Also on Tuesday, Florida Gov. Ron DeSantis signed a laweffectively banning transgender student athletesfrom participating on teams associated with their gender identity, the latest in a series of Republican-backed state bills regarding transgender rights.Left- and center-rated outlets were more likely to publish opinion articles\u00a0about\u00a0Pride Month, with some outlets on all sides covering news stories like Biden's statement. Perspectives varied by topic, with some focusing on the celebration itself and others discussing recent controversies.",
    "story": {
        "left": [
            "https://www.cbc.ca/news/opinion/opinion-rainbow-capitalism-pride-month-1.6042417?cmp=rss",
            "https://www.washingtonpost.com/opinions/2021/06/01/pride-month-begins-republicans-double-down-restricting-transgender-americans/"
        ],
        "center": [],
        "right": [
            "https://townhall.com/columnists/ryanbomberger/2021/05/31/patriotism-and-pride-n2590245"
        ]
    }
}