{
    "headline": "Sandra Day Oconnor First Woman Serve Supreme Court Announces Dementia Diagnosis",
    "summary": "Former Supreme Court Justice Sandra Day O'Connor, the first woman to serve on the high court, announced that she has been diagnosed with dementia and is retiring from public life. In a letter to the American people, she expressed her strong belief in \"working collaboratively together in communities and in government to solve problems, putting country and the common good above party and self-interest, and holding our key governmental institutions accountable.\"",
    "story": {
        "left": [
            "https://www.buzzfeednews.com/article/chrisgeidner/sandra-day-oconnor-dementia-diagnosis-alzheimers",
            "https://www.usatoday.com/story/news/politics/onpolitics/2018/10/23/sandra-day-oconnor-dementia-alzheimers-letter-statement/1738512002/"
        ],
        "center": [],
        "right": [
            "https://www.washingtonexaminer.com/policy/courts/justice-sandra-day-oconnor-has-beginning-stages-of-dementia"
        ]
    }
}