{
    "headline": "Ukraine Declare 30 Day State Emergency",
    "summary": "On Wednesday, Ukraine's National Security and Defense Council announced that a 30-day\u00a0state of emergency will be introduced across all parts of Ukraine under government control.The measure is expected to be approved by the Ukrainian Parliament within 48 hours.\u00a0 Council\u00a0Secretary Oleksiy Danilov said the declaration\u00a0would bolster \"public order and security at critical infrastructure facilities\"\u00a0and heighten inspections on\u00a0some transportation.The moves come one day after Russian President Vladimir Putin was granted the power by the Federation Council\u00a0to send Russian military forces outside\u00a0its borders. Meanwhile, the U.S.,\u00a0the E.U.\u00a0and their allies areimposing sanctionsonPutin's decision to recognize two Ukrainian territories\u2014\u00a0Donetsk\u00a0and Luhansk\u00a0\u2014 as independent republics, and to send Russian troops there.",
    "story": {
        "left": [
            "https://www.cbsnews.com/news/russia-ukraine-news-emergency-declaration-reservists-called-us-putin-sanctions/"
        ],
        "center": [
            "https://www.reuters.com/world/europe/ukraine-impose-state-emergency-says-top-security-official-2022-02-23/"
        ],
        "right": [
            "https://nypost.com/2022/02/23/ukraine-to-declare-state-of-emergency-as-putin-brags/"
        ]
    }
}