{
    "headline": "Virginia Governor Apologizes Racist Yearbook Photo",
    "summary": "Governor of Virginia, Ralph Northam, faces pressure to resign after admitting that he posed in a racist costume for a photo more than 30 years ago.",
    "story": {
        "left": [
            "https://www.nytimes.com/2019/02/02/us/politics/ralph-northam-virginia-governor.html"
        ],
        "center": [
            "https://www.bbc.com/news/world-us-canada-47098776"
        ],
        "right": [
            "https://www.washingtontimes.com/news/2019/feb/1/virginia-democrats-turn-northam-demand-resignation/"
        ]
    }
}