{
    "headline": "Chuck Todd Says Meet Press Not Going Give Time Climate Deniers",
    "summary": "MSNBC host Chuck Todd said on Sunday that his show is \"not going to give time to climate deniers\" before hosting an hourlong panel on the impact of climate change. Some criticized Todd for omitting the other side of the argument, particularly as there are conflicting studies over the likelihood and severity of certain consequences as well as the level that human activity ultimately plays.",
    "story": {
        "left": [
            "https://www.huffingtonpost.com/entry/chuck-todd-climate-deniers_us_5c2998e2e4b05c88b701abd7"
        ],
        "center": [
            "https://thehill.com/homenews/sunday-talk-shows/423264-chuck-todd-says-his-show-is-not-going-to-give-time-to-climate"
        ],
        "right": [
            "https://www.washingtontimes.com/news/2018/dec/30/chuck-todd-climate-deniers-banned-meet-press/"
        ]
    }
}