{
    "headline": "Citing Inflation And Jobs Growth Federal Reserve Signals Interest Rate Hike Soon",
    "summary": "With \u201cinflationwell above 2 percent and astrong labor market,\u201d the Federal Reserve suggested Wednesday that it would soonraise its benchmark interest rate. Many experts expect the rate hike to come in March.\u201cProgress onvaccinationsand an easing ofsupply constraintsare expected to support continued gains in economic activity and employment as well as a reduction in inflation,\u201d the central bank\u00a0said in astatement. Key to the Fed\u2019s interest rate decision is the fear that higher rates would hurt economic growth and employment; majorstock indexesturned negative on Wednesday after the central bank\u2019s announcement. Addressing those concerns, Fed Chairman Jerome Powell said, \u201cI think there\u2019s quite a bit of room to raise interest rates without threatening the labor market.\u201d The benchmark interest rate in question is thefederal funds rate, the rate at which banks lend to each other overnight to meet asset reserve requirements. The Fedlast raised interest ratesin December 2018.Coverage was mostly balanced and more common in business-focused outlets. Coverage in some outlets on the right emphasized 2021\u2019s high inflation; aFox Business(Lean Right) headline included the phrase \u201cinterest rate hike could come 'soon' as inflation rages.\u201d",
    "story": {
        "left": [
            "https://www.washingtonpost.com/business/2022/01/26/stocks-markets-federal-reserve/",
            "https://www.cnbc.com/2022/01/26/fed-decision-january-2022-.html"
        ],
        "center": [],
        "right": [
            "https://www.washingtonexaminer.com/policy/economy/fed-signals-first-interest-rate-hike-coming-soon-as-it-scrambles-to-curb-inflation"
        ]
    }
}