{
    "headline": "Documents Taken Trump Contained Classified Information National Archives Says",
    "summary": "Some of the White House documents taken to Mar-a-Lago byformer President Donald Trumpcontained \u201cclassified national security information,\u201d theNational Archivessaid in a Fridayletterto theHouse Oversight Committee.The presence of classified information further opened the possibility that Trump violatedfederal record-keeping laws. The letter also confirmedearlierreportingon the National Archives\u2019 coordination with the Justice Department on the matter. The National Archives previouslyconfirmed the documents\u2019 existenceon Feb. 7, saying it had arranged to take possession of the documents in mid-January after conversations with Trump\u2019s representatives in 2021. According to aWashington Post (Lean Left)report, some of the documents included letters from former President Barack Obama andNorth Korean leader Kim Jong Un.While several left-rated outlets featured the story at the top of their homepages,\u00a0right-rated outlets were less likely to feature the story prominently. Some coverage in left-rated outlets said Trump had \u201cimproperly\u201d taken the documents.",
    "story": {
        "left": [
            "https://www.theguardian.com/us-news/2022/feb/18/donald-trump-classified-material-national-archives"
        ],
        "center": [
            "https://thehill.com/policy/national-security/594946-archives-confirms-trump-records-at-mar-a-lago-included-classified"
        ],
        "right": [
            "https://www.washingtonexaminer.com/news/national-archives-finds-records-with-classified-information-at-trumps-mar-a-lago-resort"
        ]
    }
}